micro/__init__.py
micro/analytics.py
micro/core.py
micro/error.py
micro/jsonredis.py
micro/micro.py
micro/ratelimit.py
micro/resource.py
micro/server.py
micro/templates.py
micro/test.py
micro/util.py
micro/webapi.py
micro/doc/application-endpoints.inc
micro/doc/collection-attributes.inc
micro/doc/collection-endpoints.inc
micro/doc/editable-attributes.inc
micro/doc/editable-endpoints.inc
micro/doc/general.inc
micro/doc/object-attributes.inc
micro/doc/orderable-endpoints.inc
micro/doc/resource-attributes.inc
micro/doc/settings-attributes.inc
micro/doc/settings-endpoints.inc
micro/doc/trashable-attributes.inc
micro/doc/trashable-endpoints.inc
micro/doc/user-attributes.inc
micro/doc/user-devices.inc
micro/doc/user-endpoints.inc
micro/doc/with-content-attributes.inc
micro/tests/__init__.py
micro/tests/ext_test_email.py
micro/tests/ext_test_notification.py
micro/tests/ext_test_resource.py
micro/tests/test_analytics.py
micro/tests/test_core.py
micro/tests/test_jsonredis.py
micro/tests/test_micro.py
micro/tests/test_ratelimit.py
micro/tests/test_resource.py
micro/tests/test_server.py
micro/tests/test_util.py
micro/tests/test_webapi.py
noyainrain.micro-0.69.0.dist-info/LICENSE.txt
noyainrain.micro-0.69.0.dist-info/METADATA
noyainrain.micro-0.69.0.dist-info/WHEEL
noyainrain.micro-0.69.0.dist-info/top_level.txt
noyainrain.micro-0.69.0.dist-info/RECORD
