Metadata-Version: 2.1
Name: noyainrain.micro
Version: 0.69.0
Summary: Toolkit for social micro web apps.
Home-page: https://github.com/noyainrain/micro
Maintainer: Sven James
Maintainer-email: sven@inrain.org
License: UNKNOWN
Platform: UNKNOWN
Classifier: Operating System :: POSIX
Classifier: License :: OSI Approved :: GNU Lesser General Public License v3 or later (LGPLv3+)
Requires-Dist: Pillow (~=8.3)
Requires-Dist: mypy-extensions (~=0.4.0)
Requires-Dist: py-vapid (~=1.3)
Requires-Dist: pywebpush (~=1.4)
Requires-Dist: redis (~=3.0)
Requires-Dist: six (~=1.15)
Requires-Dist: tornado (~=6.0)
Requires-Dist: typing-extensions (~=3.6)
